PaIRS_UniNa/Calibration_Tab.py
PaIRS_UniNa/Changes.txt
PaIRS_UniNa/Custom_Top.py
PaIRS_UniNa/Explorer.py
PaIRS_UniNa/FolderLoop.py
PaIRS_UniNa/Input_Tab.py
PaIRS_UniNa/Input_Tab_CalVi.py
PaIRS_UniNa/Input_Tab_tools.py
PaIRS_UniNa/Log_Tab.py
PaIRS_UniNa/Output_Tab.py
PaIRS_UniNa/PaIRS.py
PaIRS_UniNa/PaIRS_PIV.py
PaIRS_UniNa/PaIRS_pypacks.py
PaIRS_UniNa/Process_Tab.py
PaIRS_UniNa/Process_Tab_CalVi.py
PaIRS_UniNa/Process_Tab_Disp.py
PaIRS_UniNa/Process_Tab_Min.py
PaIRS_UniNa/ResizePopup.py
PaIRS_UniNa/SPIVCalHelp.py
PaIRS_UniNa/Saving_tools.py
PaIRS_UniNa/TabTools.py
PaIRS_UniNa/Vis_Tab.py
PaIRS_UniNa/Vis_Tab_CalVi.py
PaIRS_UniNa/Whatsnew.py
PaIRS_UniNa/_PaIRS_PIV.pyd
PaIRS_UniNa/__init__.py
PaIRS_UniNa/__main__.py
PaIRS_UniNa/addwidgets_ps.py
PaIRS_UniNa/calib.py
PaIRS_UniNa/calibView.py
PaIRS_UniNa/gPaIRS.py
PaIRS_UniNa/gPalette.py
PaIRS_UniNa/listLib.py
PaIRS_UniNa/mtfPIV.py
PaIRS_UniNa/parForMulti.py
PaIRS_UniNa/parForWorkers.py
PaIRS_UniNa/pivParFor.py
PaIRS_UniNa/plt_util.py
PaIRS_UniNa/preProcParFor.py
PaIRS_UniNa/procTools.py
PaIRS_UniNa/readcfg.py
PaIRS_UniNa/rqrdpckgs.txt
PaIRS_UniNa/stereoPivParFor.py
PaIRS_UniNa/tAVarie.py
PaIRS_UniNa/tabSplitter.py
PaIRS_UniNa/ui_Calibration_Tab.py
PaIRS_UniNa/ui_Custom_Top.py
PaIRS_UniNa/ui_Input_Tab.py
PaIRS_UniNa/ui_Input_Tab_CalVi.py
PaIRS_UniNa/ui_Log_Tab.py
PaIRS_UniNa/ui_Output_Tab.py
PaIRS_UniNa/ui_Process_Tab.py
PaIRS_UniNa/ui_Process_Tab_CalVi.py
PaIRS_UniNa/ui_Process_Tab_Disp.py
PaIRS_UniNa/ui_Process_Tab_Min.py
PaIRS_UniNa/ui_ResizePopup.py
PaIRS_UniNa/ui_Vis_Tab.py
PaIRS_UniNa/ui_Vis_Tab_CalVi.py
PaIRS_UniNa/ui_Whatsnew.py
PaIRS_UniNa/ui_gPairs.py
PaIRS_UniNa/ui_infoPaIRS.py
PaIRS_UniNa/whatsnew.txt
PaIRS_UniNa/icons/abort.png
PaIRS_UniNa/icons/about.png
PaIRS_UniNa/icons/align_all.png
PaIRS_UniNa/icons/announcement.png
PaIRS_UniNa/icons/automatic_levels_off.png
PaIRS_UniNa/icons/automatic_levels_on.png
PaIRS_UniNa/icons/automatic_off.png
PaIRS_UniNa/icons/automatic_on.png
pairs_unina-0.2.10.dist-info/METADATA
pairs_unina-0.2.10.dist-info/WHEEL
pairs_unina-0.2.10.dist-info/top_level.txt
pairs_unina-0.2.10.dist-info/RECORD
