Metadata-Version: 2.4
Name: PaIRS_UniNa
Version: 0.2.10
Summary: PaIRS - Particle Image Reconstruction Software
Home-page: https://pairs.unina.it/
Author: Gerardo Paolillo and Tommaso Astarita
Author-email: etfd@unina.it
License: LGPL-3.0-or-later
Keywords: PIV,PaIRS
Classifier: Programming Language :: Python :: 3
Classifier: Operating System :: MacOS
Classifier: Operating System :: Microsoft :: Windows
Classifier: Operating System :: POSIX :: Linux
Requires-Python: >=3.10
Requires-Dist: scipy>=1.14.0
Requires-Dist: matplotlib>=3.9.0
Requires-Dist: pillow>=10.4.0
Requires-Dist: numpy>=2.0.0
Requires-Dist: pyside6>=6.7.0
Requires-Dist: unidecode>=1.3.0
Requires-Dist: psutil>=6.0.0
Requires-Dist: certifi>=2025.7.14
Dynamic: author
Dynamic: author-email
Dynamic: classifier
Dynamic: description
Dynamic: description-content-type
Dynamic: home-page
Dynamic: keywords
Dynamic: license
Dynamic: requires-dist
Dynamic: requires-python
Dynamic: summary
